asn1ate/__init__.py
asn1ate/parser.py
asn1ate/pyasn1gen.py
asn1ate/sema.py
asn1ate/test.py
asn1ate/support/__init__.py
asn1ate/support/pygen.py
asn1ate-0.6.0.dist-info/LICENSE.txt
asn1ate-0.6.0.dist-info/LICENSE.txte
asn1ate-0.6.0.dist-info/METADATA
asn1ate-0.6.0.dist-info/WHEEL
asn1ate-0.6.0.dist-info/entry_points.txt
asn1ate-0.6.0.dist-info/top_level.txt
asn1ate-0.6.0.dist-info/RECORD
