Metadata-Version: 2.1
Name: asn1ate
Version: 0.6.0
Summary: ASN.1 translation library.
Home-page: http://github.com/kimgr/asn1ate
Author: Kim Gräsman
Author-email: kim.grasman@gmail.com
License: BSD
Platform: any
Classifier: Development Status :: 3 - Alpha
Classifier: Intended Audience :: Developers
Classifier: License :: OSI Approved :: BSD License
Classifier: Operating System :: OS Independent
Classifier: Programming Language :: Python
Classifier: Programming Language :: Python :: 3
Classifier: Topic :: Software Development :: Code Generators
Requires-Dist: pyparsing (>=2.0.0)
